windows_dscp_fix-0.2.1.dist-info/METADATA
windows_dscp_fix-0.2.1.dist-info/WHEEL
windows_dscp_fix/__init__.py
windows_dscp_fix/windows_dscp_fix.cp311-win_amd64.pyd
windows_dscp_fix-0.2.1.dist-info/RECORD
