Metadata-Version: 2.1
Name: windows-dscp-fix
Version: 0.2.1
Classifier: Programming Language :: Rust
Classifier: Programming Language :: Python :: Implementation :: CPython
Classifier: Programming Language :: Python :: Implementation :: PyPy
Summary: fix setsockopt behavior for ToS/DSCP on Windows.
Keywords: windows,network,socket,development,tos,dscp
Author-email: sudo_free <sudofree@163.com>
Requires-Python: >=3.7
Project-URL: Homepage, https://github.com/iamhyc/windows-dscp-fix
Project-URL: Bug Reports, https://github.com/iamhyc/windows-dscp-fix/issues
